__init__.py
github_client.py
main.py
commands/__init__.py
commands/find_python_library.py
commands/find_python_version.py
gh_inspector-0.0.1.dist-info/METADATA
gh_inspector-0.0.1.dist-info/WHEEL
gh_inspector-0.0.1.dist-info/entry_points.txt
gh_inspector-0.0.1.dist-info/licenses/LICENSE
gh_inspector-0.0.1.dist-info/RECORD
