Metadata-Version: 2.4
Name: gh-inspector
Version: 0.0.1
Summary: A CLI tool using gh to rapidly locate and inspect files in remote GitHub repositories without cloning.
Author-email: Alejandro Cabello Jiménez <alejandro.cabello@es.python.org>
License: MIT
License-File: LICENSE
Requires-Python: >=3.10
Requires-Dist: networkx>=3.0
Requires-Dist: numpy>=1.24.0
Requires-Dist: packaging>=21.0
Requires-Dist: plotly>=5.14.0
Requires-Dist: rich>=13.0.0
Requires-Dist: tqdm>=4.65.0
Requires-Dist: typer>=0.9.0
Provides-Extra: dev
Requires-Dist: pip-tools>=7.0.0; extra == 'dev'
Requires-Dist: pre-commit>=3.0.0; extra == 'dev'
Requires-Dist: pytest>=7.0.0; extra == 'dev'
Requires-Dist: ruff>=0.8.0; extra == 'dev'
